mandolin_python_client/__init__.py
mandolin_python_client/api_client.py
mandolin_python_client/api_response.py
mandolin_python_client/configuration.py
mandolin_python_client/exceptions.py
mandolin_python_client/py.typed
mandolin_python_client/rest.py
mandolin_python_client/api/__init__.py
mandolin_python_client/api/analyzers_api.py
mandolin_python_client/api/converters_api.py
mandolin_python_client/api/default_api.py
mandolin_python_client/models/__init__.py
mandolin_python_client/models/analysis_tika_result.py
mandolin_python_client/models/analysis_yara_result.py
mandolin_python_client/models/analyzer_result_tika_result.py
mandolin_python_client/models/analyzer_result_yara_result.py
mandolin_python_client/models/http_validation_error.py
mandolin_python_client/models/thumbnail_strategy.py
mandolin_python_client/models/tika_result.py
mandolin_python_client/models/validation_error.py
mandolin_python_client/models/validation_error_loc_inner.py
mandolin_python_client/models/yara_match.py
mandolin_python_client/models/yara_result.py
mandolin_python_client/models/yara_string.py
mandolin_python_client/models/yara_string_instance.py
mandolin_python_client-1.0.2.dist-info/METADATA
mandolin_python_client-1.0.2.dist-info/WHEEL
mandolin_python_client-1.0.2.dist-info/top_level.txt
mandolin_python_client-1.0.2.dist-info/RECORD
