Metadata-Version: 2.4
Name: mandolin-python-client
Version: 1.0.2
Summary: Mandolin
Home-page: https://github.com/PiRogueToolSuite/mandolin-python-client
Author: U+039b
Author-email: contact@defensive-lab.agency
License: GNU General Public License v3.0
Requires-Dist: urllib3<3.0.0,>=1.25.3
Requires-Dist: python-dateutil>=2.8.2
Requires-Dist: pydantic>=2
Requires-Dist: typing-extensions>=4.7.1
Dynamic: author
Dynamic: author-email
Dynamic: description
Dynamic: description-content-type
Dynamic: home-page
Dynamic: license
Dynamic: requires-dist
Dynamic: summary
